cache_return/__init__.py
cache_return-0.1.2.dist-info/LICENSE
cache_return-0.1.2.dist-info/METADATA
cache_return-0.1.2.dist-info/WHEEL
cache_return-0.1.2.dist-info/top_level.txt
cache_return-0.1.2.dist-info/RECORD
