Metadata-Version: 2.1
Name: cache_return
Version: 0.1.2
Summary: A library providing a decorator wrapper for adding the caching mechanism to functions.
Author-email: Cody Xiaozhan Yang <xiaozhan.yang@icloud.com>
License: MIT License
Keywords: cache,return,result,debug
Classifier: Programming Language :: Python :: 3
Classifier: License :: OSI Approved :: MIT License
Classifier: Operating System :: OS Independent
Requires-Python: >=3.8
License-File: LICENSE
